vecfield/__init__.py
vecfield/_version.py
vecfield/field.py
vecfield/grid.py
vecfield/operators.py
vecfield/vector.py
vecfield/viz.py
vecfield_physics-0.1.0.dist-info/METADATA
vecfield_physics-0.1.0.dist-info/WHEEL
vecfield_physics-0.1.0.dist-info/top_level.txt
vecfield_physics-0.1.0.dist-info/RECORD
