Metadata-Version: 2.4
Name: vecfield-physics
Version: 0.1.0
Summary: Numerical vector calculus for physics
Author: Noah Ryan
License: MIT
Requires-Python: >=3.9
Requires-Dist: numpy
Requires-Dist: matplotlib
